django_never_cache/__init__.py
django_never_cache/apps.py
django_never_cache/decorators.py
django_never_cache/middelwares.py
django_never_cache/mixins.py
django_never_cache-0.1.2.dist-info/METADATA
django_never_cache-0.1.2.dist-info/WHEEL
django_never_cache-0.1.2.dist-info/licenses/LICENSE
django_never_cache-0.1.2.dist-info/RECORD
